[
    {
        "hora": "08:50",
        "origen": "Figueres-Vilafant",
        "tren": "AVE 03092",
        "via": "5"
    },
    {
        "hora": "09:15",
        "origen": "Lleida Pirineus",
        "tren": "AVANT 08087",
        "via": "1"
    },
    {
        "hora": "10:00",
        "origen": "Madrid Puerta de Atocha Almudena Grandes",
        "tren": "OUIGO 06471",
        "via": ""
    },
    {
        "hora": "10:04",
        "origen": "València Estació del Nord",
        "tren": "INTERCITY 01072",
        "via": ""
    },
    {
        "hora": "10:05",
        "origen": "Figueres-Vilafant",
        "tren": "EUROMED 01100",
        "via": "2"
    },
    {
        "hora": "10:17",
        "origen": "Madrid Puerta de Atocha Almudena Grandes",
        "tren": "AVE 03301",
        "via": ""
    },
    {
        "hora": "10:31",
        "origen": "Madrid Puerta de Atocha Almudena Grandes",
        "tren": "IRYO 06071",
        "via": ""
    },
    {
        "hora": "11:16",
        "origen": "Madrid Puerta de Atocha Almudena Grandes",
        "tren": "AVE 03073",
        "via": ""
    }
]